setup.py
django_openkm.egg-info/PKG-INFO
django_openkm.egg-info/SOURCES.txt
django_openkm.egg-info/dependency_links.txt
django_openkm.egg-info/requires.txt
django_openkm.egg-info/top_level.txt
openkm/__init__.py
openkm/client.py
openkm/exceptions.py
openkm/facades.py
openkm/models.py
openkm/sync.py
openkm/tests.py
openkm/utils.py
openkm/views.py