Metadata-Version: 1.0
Name: django-openkm
Version: 0.5-pre-alpha
Summary: A Python client library and functionality for the OpenKM document management system.
Home-page: https://github.com/tangentlabs/django-openkm
Author: Phil Tysoe
Author-email: philip.tysoe@tangentlabs.co.uk
License: BSD
Keywords: OpenKM,Django,document management
Platform: linux
Classifier: Environment :: Web Environment
Classifier: Framework :: Django
Classifier: Intended Audience :: Developers
Classifier: License :: OSI Approved :: BSD License
Classifier: Operating System :: Unix
Classifier: Programming Language :: Python
